lightning_client/__init__.py
lightning_client/client.py
lightning_client/lightning_pb2.py
lightning_client/lightning_pb2_grpc.py
lightning_client/router_pb2.py
lightning_client/router_pb2_grpc.py
lightning_client_mcp-0.0.3.dist-info/licenses/LICENSE
lightning_client_mcp-0.0.3.dist-info/METADATA
lightning_client_mcp-0.0.3.dist-info/WHEEL
lightning_client_mcp-0.0.3.dist-info/top_level.txt
lightning_client_mcp-0.0.3.dist-info/RECORD
